{"hotspot":{"visible":true,"radius":575,"intensity":5,"deformationAmount":1.6,"deformationFrequency":0.01,"deformationSeed":134,"alpha":100,"angle":0,"hue":48,"saturation":27,"anamorph":0},"streak":{"visible":true,"thickness":68,"width":691,"intensity":0,"count":3,"angle":30,"shift":23,"alpha":100,"hue":51,"saturation":18},"ring":{"visible":true,"radius":311,"thickness":83,"blur":13,"cropSize":0,"cropHardness":50,"alpha":21,"hue":45,"saturation":100,"anamorph":0},"miIris":{"visible":true,"radius":49,"sides":5,"roundness":100,"angle":0,"fillAlpha":25,"fringeAlpha":50,"fringeSize":10,"blur":16,"countAway":5,"countTowards":16,"spread":30,"sizeVariance":37,"perspective":100,"alphaVariance":50,"seed":329,"hue":55,"saturation":32,"hueVariance":30,"anamorph":0},"glow":{"visible":true,"radius":1203,"alpha":50,"softening":70,"hue":45,"saturation":35,"anamorph":0},"lensOrbs":{"visible":true,"radius":24,"sides":6,"roundness":12,"angle":0,"fillAlpha":1,"fringeAlpha":2,"fringeSize":12,"blur":2,"count":99,"threshold":987,"seed":807,"sizeVariance":0,"alphaVariance":50,"hue":33,"saturation":11,"hueVariance":22,"anamorph":0}}